README
pynoid.py
setup.py
pynoid.egg-info/PKG-INFO
pynoid.egg-info/SOURCES.txt
pynoid.egg-info/dependency_links.txt
pynoid.egg-info/top_level.txt