Metadata-Version: 1.0
Name: pynoid
Version: 0.1
Summary: A simple minter for opaque identifers inspired by California Digital Library's NOID.
Home-page: UNKNOWN
Author: t. johnson
Author-email: thomas.johnson@oregonstate.edu
License: UNKNOWN
Platform: UNKNOWN
